setup.py
Distributions_Python/Binomialdistribution.py
Distributions_Python/Gaussiandistribution.py
Distributions_Python/Generaldistribution.py
Distributions_Python/__init__.py
Distributions_Python.egg-info/PKG-INFO
Distributions_Python.egg-info/SOURCES.txt
Distributions_Python.egg-info/dependency_links.txt
Distributions_Python.egg-info/not-zip-safe
Distributions_Python.egg-info/top_level.txt